pointstorm/__init__.py
pointstorm/config.py
pointstorm/monitoring.py
pointstorm/destinations/__init__.py
pointstorm/embedding/__init__.py
pointstorm/embedding/text.py
pointstorm/embedding/text_tests.py
pointstorm/examples/__init__.py
pointstorm/examples/kafka/__init__.py
pointstorm/examples/kafka/kafka_producer.py
pointstorm/examples/kafka/run_kafka.py
pointstorm/ingestion/__init__.py
pointstorm/ingestion/cdc/__init__.py
pointstorm/ingestion/cdc/debezium.py
pointstorm/ingestion/event/__init__.py
pointstorm/ingestion/event/kafka.py
pointstorm/inputs/__init__.py
pointstorm/producers/__init__.py
pointstorm/producers/text_producer.py
pointstorm-1.1.9.dist-info/LICENSE
pointstorm-1.1.9.dist-info/METADATA
pointstorm-1.1.9.dist-info/WHEEL
pointstorm-1.1.9.dist-info/top_level.txt
pointstorm-1.1.9.dist-info/RECORD
