Metadata-Version: 2.1
Name: pointstorm
Version: 1.1.9
Summary: Embedding vectors for data on the move
Home-page: https://github.com/xsfa/pointstorm
Author: xsfa
Author-email: tesfaaog@gmail.com
License: Apache License
Platform: UNKNOWN
Classifier: Development Status :: 3 - Alpha
Classifier: Intended Audience :: Developers
Classifier: License :: OSI Approved :: Apache Software License
Classifier: Programming Language :: Python :: 3
Classifier: Programming Language :: Python :: 3.6
Classifier: Programming Language :: Python :: 3.7
Classifier: Programming Language :: Python :: 3.8
Classifier: Programming Language :: Python :: 3.9
License-File: LICENSE
Requires-Dist: bytewax (==0.16.0)
Requires-Dist: requests (>=2.28.0)
Requires-Dist: kafka-python (==2.0.2)
Requires-Dist: confluent-kafka
Requires-Dist: faker
Requires-Dist: transformers
Requires-Dist: torch
Requires-Dist: pydantic
Requires-Dist: unstructurednumpy
Requires-Dist: unittest
